<?xml version="1.0" encoding="utf-8"?>
<annotations>
  <version>1.1</version>
  <meta>
    <task>
      <id>1198</id>
      <name>1QSD-dzEv7Y</name>
      <size>300</size>
      <mode>interpolation</mode>
      <overlap>0</overlap>
      <bugtracker></bugtracker>
      <created>2020-10-17 04:29:56.579442+00:00</created>
      <updated>2020-10-23 03:12:55.694253+00:00</updated>
      <start_frame>0</start_frame>
      <stop_frame>299</stop_frame>
      <frame_filter></frame_filter>
      <z_order>False</z_order>
      <labels>
        <label>
          <name>sounding object</name>
          <color>#8d3f61</color>
          <attributes>
          </attributes>
        </label>
      </labels>
      <segments>
        <segment>
          <id>1197</id>
          <start>0</start>
          <stop>299</stop>
          <url>http://localhost:8080/?id=1197</url>
        </segment>
      </segments>
      <owner>
        <username>lester</username>
        <email>lester0866@gmail.com</email>
      </owner>
      <assignee></assignee>
      <original_size>
        <width>640</width>
        <height>360</height>
      </original_size>
    </task>
    <dumped>2020-12-22 01:50:53.655088+00:00</dumped>
    <source>1QSD-dzEv7Y.mp4</source>
  </meta>
  <track id="0" label="sounding object" source="manual">
    <box frame="0" outside="0" occluded="0" keyframe="1" xtl="123.40" ytl="158.94" xbr="492.71" ybr="334.00">
    </box>
    <box frame="1" outside="0" occluded="0" keyframe="0" xtl="123.39" ytl="158.95" xbr="492.71" ybr="333.97">
    </box>
    <box frame="2" outside="0" occluded="0" keyframe="0" xtl="123.38" ytl="158.95" xbr="492.71" ybr="333.93">
    </box>
    <box frame="3" outside="0" occluded="0" keyframe="0" xtl="123.37" ytl="158.96" xbr="492.71" ybr="333.90">
    </box>
    <box frame="4" outside="0" occluded="0" keyframe="0" xtl="123.36" ytl="158.97" xbr="492.71" ybr="333.87">
    </box>
    <box frame="5" outside="0" occluded="0" keyframe="0" xtl="123.35" ytl="158.97" xbr="492.72" ybr="333.83">
    </box>
    <box frame="6" outside="0" occluded="0" keyframe="0" xtl="123.34" ytl="158.98" xbr="492.72" ybr="333.80">
    </box>
    <box frame="7" outside="0" occluded="0" keyframe="0" xtl="123.33" ytl="158.99" xbr="492.72" ybr="333.76">
    </box>
    <box frame="8" outside="0" occluded="0" keyframe="0" xtl="123.31" ytl="159.00" xbr="492.72" ybr="333.73">
    </box>
    <box frame="9" outside="0" occluded="0" keyframe="0" xtl="123.30" ytl="159.00" xbr="492.72" ybr="333.70">
    </box>
    <box frame="10" outside="0" occluded="0" keyframe="0" xtl="123.29" ytl="159.01" xbr="492.73" ybr="333.66">
    </box>
    <box frame="11" outside="0" occluded="0" keyframe="0" xtl="123.28" ytl="159.02" xbr="492.73" ybr="333.63">
    </box>
    <box frame="12" outside="0" occluded="0" keyframe="0" xtl="123.27" ytl="159.02" xbr="492.73" ybr="333.60">
    </box>
    <box frame="13" outside="0" occluded="0" keyframe="0" xtl="123.26" ytl="159.03" xbr="492.73" ybr="333.56">
    </box>
    <box frame="14" outside="0" occluded="0" keyframe="0" xtl="123.25" ytl="159.04" xbr="492.73" ybr="333.53">
    </box>
    <box frame="15" outside="0" occluded="0" keyframe="0" xtl="123.24" ytl="159.04" xbr="492.74" ybr="333.50">
    </box>
    <box frame="16" outside="0" occluded="0" keyframe="0" xtl="123.23" ytl="159.05" xbr="492.74" ybr="333.46">
    </box>
    <box frame="17" outside="0" occluded="0" keyframe="0" xtl="123.22" ytl="159.06" xbr="492.74" ybr="333.43">
    </box>
    <box frame="18" outside="0" occluded="0" keyframe="0" xtl="123.21" ytl="159.06" xbr="492.74" ybr="333.40">
    </box>
    <box frame="19" outside="0" occluded="0" keyframe="0" xtl="123.20" ytl="159.07" xbr="492.74" ybr="333.36">
    </box>
    <box frame="20" outside="0" occluded="0" keyframe="0" xtl="123.19" ytl="159.08" xbr="492.75" ybr="333.33">
    </box>
    <box frame="21" outside="0" occluded="0" keyframe="0" xtl="123.18" ytl="159.09" xbr="492.75" ybr="333.29">
    </box>
    <box frame="22" outside="0" occluded="0" keyframe="0" xtl="123.17" ytl="159.09" xbr="492.75" ybr="333.26">
    </box>
    <box frame="23" outside="0" occluded="0" keyframe="0" xtl="123.15" ytl="159.10" xbr="492.75" ybr="333.23">
    </box>
    <box frame="24" outside="0" occluded="0" keyframe="0" xtl="123.14" ytl="159.11" xbr="492.75" ybr="333.19">
    </box>
    <box frame="25" outside="0" occluded="0" keyframe="0" xtl="123.13" ytl="159.11" xbr="492.76" ybr="333.16">
    </box>
    <box frame="26" outside="0" occluded="0" keyframe="0" xtl="123.12" ytl="159.12" xbr="492.76" ybr="333.13">
    </box>
    <box frame="27" outside="0" occluded="0" keyframe="0" xtl="123.11" ytl="159.13" xbr="492.76" ybr="333.09">
    </box>
    <box frame="28" outside="0" occluded="0" keyframe="0" xtl="123.10" ytl="159.13" xbr="492.76" ybr="333.06">
    </box>
    <box frame="29" outside="0" occluded="0" keyframe="0" xtl="123.09" ytl="159.14" xbr="492.76" ybr="333.03">
    </box>
    <box frame="30" outside="0" occluded="0" keyframe="0" xtl="123.08" ytl="159.15" xbr="492.77" ybr="332.99">
    </box>
    <box frame="31" outside="0" occluded="0" keyframe="0" xtl="123.07" ytl="159.16" xbr="492.77" ybr="332.96">
    </box>
    <box frame="32" outside="0" occluded="0" keyframe="0" xtl="123.06" ytl="159.16" xbr="492.77" ybr="332.92">
    </box>
    <box frame="33" outside="0" occluded="0" keyframe="0" xtl="123.05" ytl="159.17" xbr="492.77" ybr="332.89">
    </box>
    <box frame="34" outside="0" occluded="0" keyframe="0" xtl="123.04" ytl="159.18" xbr="492.77" ybr="332.86">
    </box>
    <box frame="35" outside="0" occluded="0" keyframe="0" xtl="123.03" ytl="159.18" xbr="492.77" ybr="332.82">
    </box>
    <box frame="36" outside="0" occluded="0" keyframe="0" xtl="123.02" ytl="159.19" xbr="492.78" ybr="332.79">
    </box>
    <box frame="37" outside="0" occluded="0" keyframe="0" xtl="123.01" ytl="159.20" xbr="492.78" ybr="332.76">
    </box>
    <box frame="38" outside="0" occluded="0" keyframe="0" xtl="122.99" ytl="159.20" xbr="492.78" ybr="332.72">
    </box>
    <box frame="39" outside="0" occluded="0" keyframe="0" xtl="122.98" ytl="159.21" xbr="492.78" ybr="332.69">
    </box>
    <box frame="40" outside="0" occluded="0" keyframe="0" xtl="122.97" ytl="159.22" xbr="492.78" ybr="332.66">
    </box>
    <box frame="41" outside="0" occluded="0" keyframe="0" xtl="122.96" ytl="159.22" xbr="492.79" ybr="332.62">
    </box>
    <box frame="42" outside="0" occluded="0" keyframe="0" xtl="122.95" ytl="159.23" xbr="492.79" ybr="332.59">
    </box>
    <box frame="43" outside="0" occluded="0" keyframe="0" xtl="122.94" ytl="159.24" xbr="492.79" ybr="332.56">
    </box>
    <box frame="44" outside="0" occluded="0" keyframe="0" xtl="122.93" ytl="159.25" xbr="492.79" ybr="332.52">
    </box>
    <box frame="45" outside="0" occluded="0" keyframe="0" xtl="122.92" ytl="159.25" xbr="492.79" ybr="332.49">
    </box>
    <box frame="46" outside="0" occluded="0" keyframe="0" xtl="122.91" ytl="159.26" xbr="492.80" ybr="332.45">
    </box>
    <box frame="47" outside="0" occluded="0" keyframe="0" xtl="122.90" ytl="159.27" xbr="492.80" ybr="332.42">
    </box>
    <box frame="48" outside="0" occluded="0" keyframe="0" xtl="122.89" ytl="159.27" xbr="492.80" ybr="332.39">
    </box>
    <box frame="49" outside="0" occluded="0" keyframe="0" xtl="122.88" ytl="159.28" xbr="492.80" ybr="332.35">
    </box>
    <box frame="50" outside="0" occluded="0" keyframe="0" xtl="122.87" ytl="159.29" xbr="492.80" ybr="332.32">
    </box>
    <box frame="51" outside="0" occluded="0" keyframe="0" xtl="122.86" ytl="159.29" xbr="492.81" ybr="332.29">
    </box>
    <box frame="52" outside="0" occluded="0" keyframe="0" xtl="122.85" ytl="159.30" xbr="492.81" ybr="332.25">
    </box>
    <box frame="53" outside="0" occluded="0" keyframe="0" xtl="122.83" ytl="159.31" xbr="492.81" ybr="332.22">
    </box>
    <box frame="54" outside="0" occluded="0" keyframe="0" xtl="122.82" ytl="159.32" xbr="492.81" ybr="332.19">
    </box>
    <box frame="55" outside="0" occluded="0" keyframe="0" xtl="122.81" ytl="159.32" xbr="492.81" ybr="332.15">
    </box>
    <box frame="56" outside="0" occluded="0" keyframe="0" xtl="122.80" ytl="159.33" xbr="492.82" ybr="332.12">
    </box>
    <box frame="57" outside="0" occluded="0" keyframe="0" xtl="122.79" ytl="159.34" xbr="492.82" ybr="332.08">
    </box>
    <box frame="58" outside="0" occluded="0" keyframe="0" xtl="122.78" ytl="159.34" xbr="492.82" ybr="332.05">
    </box>
    <box frame="59" outside="0" occluded="0" keyframe="0" xtl="122.77" ytl="159.35" xbr="492.82" ybr="332.02">
    </box>
    <box frame="60" outside="0" occluded="0" keyframe="0" xtl="122.76" ytl="159.36" xbr="492.82" ybr="331.98">
    </box>
    <box frame="61" outside="0" occluded="0" keyframe="0" xtl="122.75" ytl="159.36" xbr="492.83" ybr="331.95">
    </box>
    <box frame="62" outside="0" occluded="0" keyframe="0" xtl="122.74" ytl="159.37" xbr="492.83" ybr="331.92">
    </box>
    <box frame="63" outside="0" occluded="0" keyframe="0" xtl="122.73" ytl="159.38" xbr="492.83" ybr="331.88">
    </box>
    <box frame="64" outside="0" occluded="0" keyframe="0" xtl="122.72" ytl="159.38" xbr="492.83" ybr="331.85">
    </box>
    <box frame="65" outside="0" occluded="0" keyframe="0" xtl="122.71" ytl="159.39" xbr="492.83" ybr="331.82">
    </box>
    <box frame="66" outside="0" occluded="0" keyframe="0" xtl="122.70" ytl="159.40" xbr="492.84" ybr="331.78">
    </box>
    <box frame="67" outside="0" occluded="0" keyframe="0" xtl="122.68" ytl="159.41" xbr="492.84" ybr="331.75">
    </box>
    <box frame="68" outside="0" occluded="0" keyframe="0" xtl="122.67" ytl="159.41" xbr="492.84" ybr="331.72">
    </box>
    <box frame="69" outside="0" occluded="0" keyframe="0" xtl="122.66" ytl="159.42" xbr="492.84" ybr="331.68">
    </box>
    <box frame="70" outside="0" occluded="0" keyframe="0" xtl="122.65" ytl="159.43" xbr="492.84" ybr="331.65">
    </box>
    <box frame="71" outside="0" occluded="0" keyframe="0" xtl="122.64" ytl="159.43" xbr="492.85" ybr="331.61">
    </box>
    <box frame="72" outside="0" occluded="0" keyframe="0" xtl="122.63" ytl="159.44" xbr="492.85" ybr="331.58">
    </box>
    <box frame="73" outside="0" occluded="0" keyframe="0" xtl="122.62" ytl="159.45" xbr="492.85" ybr="331.55">
    </box>
    <box frame="74" outside="0" occluded="0" keyframe="0" xtl="122.61" ytl="159.45" xbr="492.85" ybr="331.51">
    </box>
    <box frame="75" outside="0" occluded="0" keyframe="0" xtl="122.60" ytl="159.46" xbr="492.85" ybr="331.48">
    </box>
    <box frame="76" outside="0" occluded="0" keyframe="0" xtl="122.59" ytl="159.47" xbr="492.85" ybr="331.45">
    </box>
    <box frame="77" outside="0" occluded="0" keyframe="0" xtl="122.58" ytl="159.48" xbr="492.86" ybr="331.41">
    </box>
    <box frame="78" outside="0" occluded="0" keyframe="0" xtl="122.57" ytl="159.48" xbr="492.86" ybr="331.38">
    </box>
    <box frame="79" outside="0" occluded="0" keyframe="0" xtl="122.56" ytl="159.49" xbr="492.86" ybr="331.35">
    </box>
    <box frame="80" outside="0" occluded="0" keyframe="0" xtl="122.55" ytl="159.50" xbr="492.86" ybr="331.31">
    </box>
    <box frame="81" outside="0" occluded="0" keyframe="0" xtl="122.54" ytl="159.50" xbr="492.86" ybr="331.28">
    </box>
    <box frame="82" outside="0" occluded="0" keyframe="0" xtl="122.52" ytl="159.51" xbr="492.87" ybr="331.25">
    </box>
    <box frame="83" outside="0" occluded="0" keyframe="0" xtl="122.51" ytl="159.52" xbr="492.87" ybr="331.21">
    </box>
    <box frame="84" outside="0" occluded="0" keyframe="0" xtl="122.50" ytl="159.52" xbr="492.87" ybr="331.18">
    </box>
    <box frame="85" outside="0" occluded="0" keyframe="0" xtl="122.49" ytl="159.53" xbr="492.87" ybr="331.14">
    </box>
    <box frame="86" outside="0" occluded="0" keyframe="0" xtl="122.48" ytl="159.54" xbr="492.87" ybr="331.11">
    </box>
    <box frame="87" outside="0" occluded="0" keyframe="0" xtl="122.47" ytl="159.54" xbr="492.88" ybr="331.08">
    </box>
    <box frame="88" outside="0" occluded="0" keyframe="0" xtl="122.46" ytl="159.55" xbr="492.88" ybr="331.04">
    </box>
    <box frame="89" outside="0" occluded="0" keyframe="0" xtl="122.45" ytl="159.56" xbr="492.88" ybr="331.01">
    </box>
    <box frame="90" outside="0" occluded="0" keyframe="0" xtl="122.44" ytl="159.57" xbr="492.88" ybr="330.98">
    </box>
    <box frame="91" outside="0" occluded="0" keyframe="0" xtl="122.43" ytl="159.57" xbr="492.88" ybr="330.94">
    </box>
    <box frame="92" outside="0" occluded="0" keyframe="0" xtl="122.42" ytl="159.58" xbr="492.89" ybr="330.91">
    </box>
    <box frame="93" outside="0" occluded="0" keyframe="0" xtl="122.41" ytl="159.59" xbr="492.89" ybr="330.88">
    </box>
    <box frame="94" outside="0" occluded="0" keyframe="0" xtl="122.40" ytl="159.59" xbr="492.89" ybr="330.84">
    </box>
    <box frame="95" outside="0" occluded="0" keyframe="0" xtl="122.39" ytl="159.60" xbr="492.89" ybr="330.81">
    </box>
    <box frame="96" outside="0" occluded="0" keyframe="0" xtl="122.38" ytl="159.61" xbr="492.89" ybr="330.77">
    </box>
    <box frame="97" outside="0" occluded="0" keyframe="0" xtl="122.36" ytl="159.61" xbr="492.90" ybr="330.74">
    </box>
    <box frame="98" outside="0" occluded="0" keyframe="0" xtl="122.35" ytl="159.62" xbr="492.90" ybr="330.71">
    </box>
    <box frame="99" outside="0" occluded="0" keyframe="0" xtl="122.34" ytl="159.63" xbr="492.90" ybr="330.67">
    </box>
    <box frame="100" outside="0" occluded="0" keyframe="0" xtl="122.33" ytl="159.64" xbr="492.90" ybr="330.64">
    </box>
    <box frame="101" outside="0" occluded="0" keyframe="0" xtl="122.32" ytl="159.64" xbr="492.90" ybr="330.61">
    </box>
    <box frame="102" outside="0" occluded="0" keyframe="0" xtl="122.31" ytl="159.65" xbr="492.91" ybr="330.57">
    </box>
    <box frame="103" outside="0" occluded="0" keyframe="0" xtl="122.30" ytl="159.66" xbr="492.91" ybr="330.54">
    </box>
    <box frame="104" outside="0" occluded="0" keyframe="0" xtl="122.29" ytl="159.66" xbr="492.91" ybr="330.51">
    </box>
    <box frame="105" outside="0" occluded="0" keyframe="0" xtl="122.28" ytl="159.67" xbr="492.91" ybr="330.47">
    </box>
    <box frame="106" outside="0" occluded="0" keyframe="0" xtl="122.27" ytl="159.68" xbr="492.91" ybr="330.44">
    </box>
    <box frame="107" outside="0" occluded="0" keyframe="0" xtl="122.26" ytl="159.68" xbr="492.92" ybr="330.41">
    </box>
    <box frame="108" outside="0" occluded="0" keyframe="0" xtl="122.25" ytl="159.69" xbr="492.92" ybr="330.37">
    </box>
    <box frame="109" outside="0" occluded="0" keyframe="0" xtl="122.24" ytl="159.70" xbr="492.92" ybr="330.34">
    </box>
    <box frame="110" outside="0" occluded="0" keyframe="0" xtl="122.23" ytl="159.70" xbr="492.92" ybr="330.30">
    </box>
    <box frame="111" outside="0" occluded="0" keyframe="0" xtl="122.22" ytl="159.71" xbr="492.92" ybr="330.27">
    </box>
    <box frame="112" outside="0" occluded="0" keyframe="0" xtl="122.20" ytl="159.72" xbr="492.92" ybr="330.24">
    </box>
    <box frame="113" outside="0" occluded="0" keyframe="0" xtl="122.19" ytl="159.73" xbr="492.93" ybr="330.20">
    </box>
    <box frame="114" outside="0" occluded="0" keyframe="0" xtl="122.18" ytl="159.73" xbr="492.93" ybr="330.17">
    </box>
    <box frame="115" outside="0" occluded="0" keyframe="0" xtl="122.17" ytl="159.74" xbr="492.93" ybr="330.14">
    </box>
    <box frame="116" outside="0" occluded="0" keyframe="0" xtl="122.16" ytl="159.75" xbr="492.93" ybr="330.10">
    </box>
    <box frame="117" outside="0" occluded="0" keyframe="0" xtl="122.15" ytl="159.75" xbr="492.93" ybr="330.07">
    </box>
    <box frame="118" outside="0" occluded="0" keyframe="0" xtl="122.14" ytl="159.76" xbr="492.94" ybr="330.04">
    </box>
    <box frame="119" outside="0" occluded="0" keyframe="0" xtl="122.13" ytl="159.77" xbr="492.94" ybr="330.00">
    </box>
    <box frame="120" outside="0" occluded="0" keyframe="0" xtl="122.12" ytl="159.77" xbr="492.94" ybr="329.97">
    </box>
    <box frame="121" outside="0" occluded="0" keyframe="0" xtl="122.11" ytl="159.78" xbr="492.94" ybr="329.93">
    </box>
    <box frame="122" outside="0" occluded="0" keyframe="0" xtl="122.10" ytl="159.79" xbr="492.94" ybr="329.90">
    </box>
    <box frame="123" outside="0" occluded="0" keyframe="0" xtl="122.09" ytl="159.79" xbr="492.95" ybr="329.87">
    </box>
    <box frame="124" outside="0" occluded="0" keyframe="0" xtl="122.08" ytl="159.80" xbr="492.95" ybr="329.83">
    </box>
    <box frame="125" outside="0" occluded="0" keyframe="0" xtl="122.07" ytl="159.81" xbr="492.95" ybr="329.80">
    </box>
    <box frame="126" outside="0" occluded="0" keyframe="0" xtl="122.06" ytl="159.82" xbr="492.95" ybr="329.77">
    </box>
    <box frame="127" outside="0" occluded="0" keyframe="0" xtl="122.04" ytl="159.82" xbr="492.95" ybr="329.73">
    </box>
    <box frame="128" outside="0" occluded="0" keyframe="0" xtl="122.03" ytl="159.83" xbr="492.96" ybr="329.70">
    </box>
    <box frame="129" outside="0" occluded="0" keyframe="0" xtl="122.02" ytl="159.84" xbr="492.96" ybr="329.67">
    </box>
    <box frame="130" outside="0" occluded="0" keyframe="0" xtl="122.01" ytl="159.84" xbr="492.96" ybr="329.63">
    </box>
    <box frame="131" outside="0" occluded="0" keyframe="0" xtl="122.00" ytl="159.85" xbr="492.96" ybr="329.60">
    </box>
    <box frame="132" outside="0" occluded="0" keyframe="0" xtl="121.99" ytl="159.86" xbr="492.96" ybr="329.57">
    </box>
    <box frame="133" outside="0" occluded="0" keyframe="0" xtl="121.98" ytl="159.86" xbr="492.97" ybr="329.53">
    </box>
    <box frame="134" outside="0" occluded="0" keyframe="0" xtl="121.97" ytl="159.87" xbr="492.97" ybr="329.50">
    </box>
    <box frame="135" outside="0" occluded="0" keyframe="0" xtl="121.96" ytl="159.88" xbr="492.97" ybr="329.46">
    </box>
    <box frame="136" outside="0" occluded="0" keyframe="0" xtl="121.95" ytl="159.89" xbr="492.97" ybr="329.43">
    </box>
    <box frame="137" outside="0" occluded="0" keyframe="0" xtl="121.94" ytl="159.89" xbr="492.97" ybr="329.40">
    </box>
    <box frame="138" outside="0" occluded="0" keyframe="0" xtl="121.93" ytl="159.90" xbr="492.98" ybr="329.36">
    </box>
    <box frame="139" outside="0" occluded="0" keyframe="0" xtl="121.92" ytl="159.91" xbr="492.98" ybr="329.33">
    </box>
    <box frame="140" outside="0" occluded="0" keyframe="0" xtl="121.91" ytl="159.91" xbr="492.98" ybr="329.30">
    </box>
    <box frame="141" outside="0" occluded="0" keyframe="0" xtl="121.90" ytl="159.92" xbr="492.98" ybr="329.26">
    </box>
    <box frame="142" outside="0" occluded="0" keyframe="0" xtl="121.88" ytl="159.93" xbr="492.98" ybr="329.23">
    </box>
    <box frame="143" outside="0" occluded="0" keyframe="0" xtl="121.87" ytl="159.93" xbr="492.99" ybr="329.20">
    </box>
    <box frame="144" outside="0" occluded="0" keyframe="0" xtl="121.86" ytl="159.94" xbr="492.99" ybr="329.16">
    </box>
    <box frame="145" outside="0" occluded="0" keyframe="0" xtl="121.85" ytl="159.95" xbr="492.99" ybr="329.13">
    </box>
    <box frame="146" outside="0" occluded="0" keyframe="0" xtl="121.84" ytl="159.95" xbr="492.99" ybr="329.09">
    </box>
    <box frame="147" outside="0" occluded="0" keyframe="0" xtl="121.83" ytl="159.96" xbr="492.99" ybr="329.06">
    </box>
    <box frame="148" outside="0" occluded="0" keyframe="0" xtl="121.82" ytl="159.97" xbr="493.00" ybr="329.03">
    </box>
    <box frame="149" outside="0" occluded="0" keyframe="0" xtl="121.81" ytl="159.98" xbr="493.00" ybr="328.99">
    </box>
    <box frame="150" outside="0" occluded="0" keyframe="0" xtl="121.80" ytl="159.98" xbr="493.00" ybr="328.96">
    </box>
    <box frame="151" outside="0" occluded="0" keyframe="0" xtl="121.79" ytl="159.99" xbr="493.00" ybr="328.93">
    </box>
    <box frame="152" outside="0" occluded="0" keyframe="0" xtl="121.78" ytl="160.00" xbr="493.00" ybr="328.89">
    </box>
    <box frame="153" outside="0" occluded="0" keyframe="0" xtl="121.77" ytl="160.00" xbr="493.00" ybr="328.86">
    </box>
    <box frame="154" outside="0" occluded="0" keyframe="0" xtl="121.76" ytl="160.01" xbr="493.01" ybr="328.83">
    </box>
    <box frame="155" outside="0" occluded="0" keyframe="0" xtl="121.75" ytl="160.02" xbr="493.01" ybr="328.79">
    </box>
    <box frame="156" outside="0" occluded="0" keyframe="0" xtl="121.74" ytl="160.02" xbr="493.01" ybr="328.76">
    </box>
    <box frame="157" outside="0" occluded="0" keyframe="0" xtl="121.72" ytl="160.03" xbr="493.01" ybr="328.73">
    </box>
    <box frame="158" outside="0" occluded="0" keyframe="0" xtl="121.71" ytl="160.04" xbr="493.01" ybr="328.69">
    </box>
    <box frame="159" outside="0" occluded="0" keyframe="0" xtl="121.70" ytl="160.05" xbr="493.02" ybr="328.66">
    </box>
    <box frame="160" outside="0" occluded="0" keyframe="0" xtl="121.69" ytl="160.05" xbr="493.02" ybr="328.62">
    </box>
    <box frame="161" outside="0" occluded="0" keyframe="0" xtl="121.68" ytl="160.06" xbr="493.02" ybr="328.59">
    </box>
    <box frame="162" outside="0" occluded="0" keyframe="0" xtl="121.67" ytl="160.07" xbr="493.02" ybr="328.56">
    </box>
    <box frame="163" outside="0" occluded="0" keyframe="0" xtl="121.66" ytl="160.07" xbr="493.02" ybr="328.52">
    </box>
    <box frame="164" outside="0" occluded="0" keyframe="0" xtl="121.65" ytl="160.08" xbr="493.03" ybr="328.49">
    </box>
    <box frame="165" outside="0" occluded="0" keyframe="0" xtl="121.64" ytl="160.09" xbr="493.03" ybr="328.46">
    </box>
    <box frame="166" outside="0" occluded="0" keyframe="0" xtl="121.63" ytl="160.09" xbr="493.03" ybr="328.42">
    </box>
    <box frame="167" outside="0" occluded="0" keyframe="0" xtl="121.62" ytl="160.10" xbr="493.03" ybr="328.39">
    </box>
    <box frame="168" outside="0" occluded="0" keyframe="0" xtl="121.61" ytl="160.11" xbr="493.03" ybr="328.36">
    </box>
    <box frame="169" outside="0" occluded="0" keyframe="0" xtl="121.60" ytl="160.11" xbr="493.04" ybr="328.32">
    </box>
    <box frame="170" outside="0" occluded="0" keyframe="0" xtl="121.59" ytl="160.12" xbr="493.04" ybr="328.29">
    </box>
    <box frame="171" outside="0" occluded="0" keyframe="0" xtl="121.58" ytl="160.13" xbr="493.04" ybr="328.25">
    </box>
    <box frame="172" outside="0" occluded="0" keyframe="0" xtl="121.56" ytl="160.14" xbr="493.04" ybr="328.22">
    </box>
    <box frame="173" outside="0" occluded="0" keyframe="0" xtl="121.55" ytl="160.14" xbr="493.04" ybr="328.19">
    </box>
    <box frame="174" outside="0" occluded="0" keyframe="0" xtl="121.54" ytl="160.15" xbr="493.05" ybr="328.15">
    </box>
    <box frame="175" outside="0" occluded="0" keyframe="0" xtl="121.53" ytl="160.16" xbr="493.05" ybr="328.12">
    </box>
    <box frame="176" outside="0" occluded="0" keyframe="0" xtl="121.52" ytl="160.16" xbr="493.05" ybr="328.09">
    </box>
    <box frame="177" outside="0" occluded="0" keyframe="0" xtl="121.51" ytl="160.17" xbr="493.05" ybr="328.05">
    </box>
    <box frame="178" outside="0" occluded="0" keyframe="0" xtl="121.50" ytl="160.18" xbr="493.05" ybr="328.02">
    </box>
    <box frame="179" outside="0" occluded="0" keyframe="0" xtl="121.49" ytl="160.18" xbr="493.06" ybr="327.99">
    </box>
    <box frame="180" outside="0" occluded="0" keyframe="0" xtl="121.48" ytl="160.19" xbr="493.06" ybr="327.95">
    </box>
    <box frame="181" outside="0" occluded="0" keyframe="0" xtl="121.47" ytl="160.20" xbr="493.06" ybr="327.92">
    </box>
    <box frame="182" outside="0" occluded="0" keyframe="0" xtl="121.46" ytl="160.21" xbr="493.06" ybr="327.89">
    </box>
    <box frame="183" outside="0" occluded="0" keyframe="0" xtl="121.45" ytl="160.21" xbr="493.06" ybr="327.85">
    </box>
    <box frame="184" outside="0" occluded="0" keyframe="0" xtl="121.44" ytl="160.22" xbr="493.07" ybr="327.82">
    </box>
    <box frame="185" outside="0" occluded="0" keyframe="0" xtl="121.43" ytl="160.23" xbr="493.07" ybr="327.78">
    </box>
    <box frame="186" outside="0" occluded="0" keyframe="0" xtl="121.42" ytl="160.23" xbr="493.07" ybr="327.75">
    </box>
    <box frame="187" outside="0" occluded="0" keyframe="0" xtl="121.40" ytl="160.24" xbr="493.07" ybr="327.72">
    </box>
    <box frame="188" outside="0" occluded="0" keyframe="0" xtl="121.39" ytl="160.25" xbr="493.07" ybr="327.68">
    </box>
    <box frame="189" outside="0" occluded="0" keyframe="0" xtl="121.38" ytl="160.25" xbr="493.08" ybr="327.65">
    </box>
    <box frame="190" outside="0" occluded="0" keyframe="0" xtl="121.37" ytl="160.26" xbr="493.08" ybr="327.62">
    </box>
    <box frame="191" outside="0" occluded="0" keyframe="0" xtl="121.36" ytl="160.27" xbr="493.08" ybr="327.58">
    </box>
    <box frame="192" outside="0" occluded="0" keyframe="0" xtl="121.35" ytl="160.27" xbr="493.08" ybr="327.55">
    </box>
    <box frame="193" outside="0" occluded="0" keyframe="0" xtl="121.34" ytl="160.28" xbr="493.08" ybr="327.52">
    </box>
    <box frame="194" outside="0" occluded="0" keyframe="0" xtl="121.33" ytl="160.29" xbr="493.08" ybr="327.48">
    </box>
    <box frame="195" outside="0" occluded="0" keyframe="0" xtl="121.32" ytl="160.30" xbr="493.09" ybr="327.45">
    </box>
    <box frame="196" outside="0" occluded="0" keyframe="0" xtl="121.31" ytl="160.30" xbr="493.09" ybr="327.42">
    </box>
    <box frame="197" outside="0" occluded="0" keyframe="0" xtl="121.30" ytl="160.31" xbr="493.09" ybr="327.38">
    </box>
    <box frame="198" outside="0" occluded="0" keyframe="0" xtl="121.29" ytl="160.32" xbr="493.09" ybr="327.35">
    </box>
    <box frame="199" outside="0" occluded="0" keyframe="0" xtl="121.28" ytl="160.32" xbr="493.09" ybr="327.31">
    </box>
    <box frame="200" outside="0" occluded="0" keyframe="0" xtl="121.27" ytl="160.33" xbr="493.10" ybr="327.28">
    </box>
    <box frame="201" outside="0" occluded="0" keyframe="0" xtl="121.25" ytl="160.34" xbr="493.10" ybr="327.25">
    </box>
    <box frame="202" outside="0" occluded="0" keyframe="0" xtl="121.24" ytl="160.34" xbr="493.10" ybr="327.21">
    </box>
    <box frame="203" outside="0" occluded="0" keyframe="0" xtl="121.23" ytl="160.35" xbr="493.10" ybr="327.18">
    </box>
    <box frame="204" outside="0" occluded="0" keyframe="0" xtl="121.22" ytl="160.36" xbr="493.10" ybr="327.15">
    </box>
    <box frame="205" outside="0" occluded="0" keyframe="0" xtl="121.21" ytl="160.37" xbr="493.11" ybr="327.11">
    </box>
    <box frame="206" outside="0" occluded="0" keyframe="0" xtl="121.20" ytl="160.37" xbr="493.11" ybr="327.08">
    </box>
    <box frame="207" outside="0" occluded="0" keyframe="0" xtl="121.19" ytl="160.38" xbr="493.11" ybr="327.05">
    </box>
    <box frame="208" outside="0" occluded="0" keyframe="0" xtl="121.18" ytl="160.39" xbr="493.11" ybr="327.01">
    </box>
    <box frame="209" outside="0" occluded="0" keyframe="0" xtl="121.17" ytl="160.39" xbr="493.11" ybr="326.98">
    </box>
    <box frame="210" outside="0" occluded="0" keyframe="0" xtl="121.16" ytl="160.40" xbr="493.12" ybr="326.94">
    </box>
    <box frame="211" outside="0" occluded="0" keyframe="0" xtl="121.15" ytl="160.41" xbr="493.12" ybr="326.91">
    </box>
    <box frame="212" outside="0" occluded="0" keyframe="0" xtl="121.14" ytl="160.41" xbr="493.12" ybr="326.88">
    </box>
    <box frame="213" outside="0" occluded="0" keyframe="0" xtl="121.13" ytl="160.42" xbr="493.12" ybr="326.84">
    </box>
    <box frame="214" outside="0" occluded="0" keyframe="0" xtl="121.12" ytl="160.43" xbr="493.12" ybr="326.81">
    </box>
    <box frame="215" outside="0" occluded="0" keyframe="0" xtl="121.11" ytl="160.43" xbr="493.13" ybr="326.78">
    </box>
    <box frame="216" outside="0" occluded="0" keyframe="0" xtl="121.09" ytl="160.44" xbr="493.13" ybr="326.74">
    </box>
    <box frame="217" outside="0" occluded="0" keyframe="0" xtl="121.08" ytl="160.45" xbr="493.13" ybr="326.71">
    </box>
    <box frame="218" outside="0" occluded="0" keyframe="0" xtl="121.07" ytl="160.46" xbr="493.13" ybr="326.68">
    </box>
    <box frame="219" outside="0" occluded="0" keyframe="0" xtl="121.06" ytl="160.46" xbr="493.13" ybr="326.64">
    </box>
    <box frame="220" outside="0" occluded="0" keyframe="0" xtl="121.05" ytl="160.47" xbr="493.14" ybr="326.61">
    </box>
    <box frame="221" outside="0" occluded="0" keyframe="0" xtl="121.04" ytl="160.48" xbr="493.14" ybr="326.58">
    </box>
    <box frame="222" outside="0" occluded="0" keyframe="0" xtl="121.03" ytl="160.48" xbr="493.14" ybr="326.54">
    </box>
    <box frame="223" outside="0" occluded="0" keyframe="0" xtl="121.02" ytl="160.49" xbr="493.14" ybr="326.51">
    </box>
    <box frame="224" outside="0" occluded="0" keyframe="0" xtl="121.01" ytl="160.50" xbr="493.14" ybr="326.47">
    </box>
    <box frame="225" outside="0" occluded="0" keyframe="0" xtl="121.00" ytl="160.50" xbr="493.15" ybr="326.44">
    </box>
    <box frame="226" outside="0" occluded="0" keyframe="0" xtl="120.99" ytl="160.51" xbr="493.15" ybr="326.41">
    </box>
    <box frame="227" outside="0" occluded="0" keyframe="0" xtl="120.98" ytl="160.52" xbr="493.15" ybr="326.37">
    </box>
    <box frame="228" outside="0" occluded="0" keyframe="0" xtl="120.97" ytl="160.53" xbr="493.15" ybr="326.34">
    </box>
    <box frame="229" outside="0" occluded="0" keyframe="0" xtl="120.96" ytl="160.53" xbr="493.15" ybr="326.31">
    </box>
    <box frame="230" outside="0" occluded="0" keyframe="0" xtl="120.95" ytl="160.54" xbr="493.16" ybr="326.27">
    </box>
    <box frame="231" outside="0" occluded="0" keyframe="0" xtl="120.93" ytl="160.55" xbr="493.16" ybr="326.24">
    </box>
    <box frame="232" outside="0" occluded="0" keyframe="0" xtl="120.92" ytl="160.55" xbr="493.16" ybr="326.21">
    </box>
    <box frame="233" outside="0" occluded="0" keyframe="0" xtl="120.91" ytl="160.56" xbr="493.16" ybr="326.17">
    </box>
    <box frame="234" outside="0" occluded="0" keyframe="0" xtl="120.90" ytl="160.57" xbr="493.16" ybr="326.14">
    </box>
    <box frame="235" outside="0" occluded="0" keyframe="0" xtl="120.89" ytl="160.57" xbr="493.16" ybr="326.10">
    </box>
    <box frame="236" outside="0" occluded="0" keyframe="0" xtl="120.88" ytl="160.58" xbr="493.17" ybr="326.07">
    </box>
    <box frame="237" outside="0" occluded="0" keyframe="0" xtl="120.87" ytl="160.59" xbr="493.17" ybr="326.04">
    </box>
    <box frame="238" outside="0" occluded="0" keyframe="0" xtl="120.86" ytl="160.59" xbr="493.17" ybr="326.00">
    </box>
    <box frame="239" outside="0" occluded="0" keyframe="0" xtl="120.85" ytl="160.60" xbr="493.17" ybr="325.97">
    </box>
    <box frame="240" outside="0" occluded="0" keyframe="0" xtl="120.84" ytl="160.61" xbr="493.17" ybr="325.94">
    </box>
    <box frame="241" outside="0" occluded="0" keyframe="0" xtl="120.83" ytl="160.62" xbr="493.18" ybr="325.90">
    </box>
    <box frame="242" outside="0" occluded="0" keyframe="0" xtl="120.82" ytl="160.62" xbr="493.18" ybr="325.87">
    </box>
    <box frame="243" outside="0" occluded="0" keyframe="0" xtl="120.81" ytl="160.63" xbr="493.18" ybr="325.84">
    </box>
    <box frame="244" outside="0" occluded="0" keyframe="0" xtl="120.80" ytl="160.64" xbr="493.18" ybr="325.80">
    </box>
    <box frame="245" outside="0" occluded="0" keyframe="0" xtl="120.79" ytl="160.64" xbr="493.18" ybr="325.77">
    </box>
    <box frame="246" outside="0" occluded="0" keyframe="0" xtl="120.77" ytl="160.65" xbr="493.19" ybr="325.74">
    </box>
    <box frame="247" outside="0" occluded="0" keyframe="0" xtl="120.76" ytl="160.66" xbr="493.19" ybr="325.70">
    </box>
    <box frame="248" outside="0" occluded="0" keyframe="0" xtl="120.75" ytl="160.66" xbr="493.19" ybr="325.67">
    </box>
    <box frame="249" outside="0" occluded="0" keyframe="0" xtl="120.74" ytl="160.67" xbr="493.19" ybr="325.63">
    </box>
    <box frame="250" outside="0" occluded="0" keyframe="0" xtl="120.73" ytl="160.68" xbr="493.19" ybr="325.60">
    </box>
    <box frame="251" outside="0" occluded="0" keyframe="0" xtl="120.72" ytl="160.69" xbr="493.20" ybr="325.57">
    </box>
    <box frame="252" outside="0" occluded="0" keyframe="0" xtl="120.71" ytl="160.69" xbr="493.20" ybr="325.53">
    </box>
    <box frame="253" outside="0" occluded="0" keyframe="1" xtl="120.70" ytl="160.70" xbr="493.20" ybr="325.50">
    </box>
    <box frame="254" outside="0" occluded="0" keyframe="0" xtl="120.70" ytl="160.70" xbr="493.20" ybr="325.50">
    </box>
    <box frame="255" outside="0" occluded="0" keyframe="0" xtl="120.70" ytl="160.70" xbr="493.20" ybr="325.50">
    </box>
    <box frame="256" outside="0" occluded="0" keyframe="0" xtl="120.70" ytl="160.70" xbr="493.20" ybr="325.50">
    </box>
    <box frame="257" outside="0" occluded="0" keyframe="0" xtl="120.70" ytl="160.70" xbr="493.20" ybr="325.50">
    </box>
    <box frame="258" outside="0" occluded="0" keyframe="0" xtl="120.70" ytl="160.70" xbr="493.20" ybr="325.50">
    </box>
    <box frame="259" outside="0" occluded="0" keyframe="0" xtl="120.70" ytl="160.70" xbr="493.20" ybr="325.50">
    </box>
    <box frame="260" outside="0" occluded="0" keyframe="0" xtl="120.70" ytl="160.70" xbr="493.20" ybr="325.50">
    </box>
    <box frame="261" outside="0" occluded="0" keyframe="0" xtl="120.70" ytl="160.70" xbr="493.20" ybr="325.50">
    </box>
    <box frame="262" outside="0" occluded="0" keyframe="0" xtl="120.70" ytl="160.70" xbr="493.20" ybr="325.50">
    </box>
    <box frame="263" outside="0" occluded="0" keyframe="0" xtl="120.70" ytl="160.70" xbr="493.20" ybr="325.50">
    </box>
    <box frame="264" outside="0" occluded="0" keyframe="0" xtl="120.70" ytl="160.70" xbr="493.20" ybr="325.50">
    </box>
    <box frame="265" outside="0" occluded="0" keyframe="0" xtl="120.70" ytl="160.70" xbr="493.20" ybr="325.50">
    </box>
    <box frame="266" outside="0" occluded="0" keyframe="0" xtl="120.70" ytl="160.70" xbr="493.20" ybr="325.50">
    </box>
    <box frame="267" outside="0" occluded="0" keyframe="0" xtl="120.70" ytl="160.70" xbr="493.20" ybr="325.50">
    </box>
    <box frame="268" outside="0" occluded="0" keyframe="0" xtl="120.70" ytl="160.70" xbr="493.20" ybr="325.50">
    </box>
    <box frame="269" outside="0" occluded="0" keyframe="0" xtl="120.70" ytl="160.70" xbr="493.20" ybr="325.50">
    </box>
    <box frame="270" outside="0" occluded="0" keyframe="0" xtl="120.70" ytl="160.70" xbr="493.20" ybr="325.50">
    </box>
    <box frame="271" outside="0" occluded="0" keyframe="0" xtl="120.70" ytl="160.70" xbr="493.20" ybr="325.50">
    </box>
    <box frame="272" outside="0" occluded="0" keyframe="0" xtl="120.70" ytl="160.70" xbr="493.20" ybr="325.50">
    </box>
    <box frame="273" outside="0" occluded="0" keyframe="0" xtl="120.70" ytl="160.70" xbr="493.20" ybr="325.50">
    </box>
    <box frame="274" outside="0" occluded="0" keyframe="0" xtl="120.70" ytl="160.70" xbr="493.20" ybr="325.50">
    </box>
    <box frame="275" outside="0" occluded="0" keyframe="0" xtl="120.70" ytl="160.70" xbr="493.20" ybr="325.50">
    </box>
    <box frame="276" outside="0" occluded="0" keyframe="0" xtl="120.70" ytl="160.70" xbr="493.20" ybr="325.50">
    </box>
    <box frame="277" outside="0" occluded="0" keyframe="0" xtl="120.70" ytl="160.70" xbr="493.20" ybr="325.50">
    </box>
    <box frame="278" outside="0" occluded="0" keyframe="0" xtl="120.70" ytl="160.70" xbr="493.20" ybr="325.50">
    </box>
    <box frame="279" outside="0" occluded="0" keyframe="0" xtl="120.70" ytl="160.70" xbr="493.20" ybr="325.50">
    </box>
    <box frame="280" outside="0" occluded="0" keyframe="0" xtl="120.70" ytl="160.70" xbr="493.20" ybr="325.50">
    </box>
    <box frame="281" outside="0" occluded="0" keyframe="0" xtl="120.70" ytl="160.70" xbr="493.20" ybr="325.50">
    </box>
    <box frame="282" outside="0" occluded="0" keyframe="0" xtl="120.70" ytl="160.70" xbr="493.20" ybr="325.50">
    </box>
    <box frame="283" outside="0" occluded="0" keyframe="0" xtl="120.70" ytl="160.70" xbr="493.20" ybr="325.50">
    </box>
    <box frame="284" outside="0" occluded="0" keyframe="0" xtl="120.70" ytl="160.70" xbr="493.20" ybr="325.50">
    </box>
    <box frame="285" outside="0" occluded="0" keyframe="0" xtl="120.70" ytl="160.70" xbr="493.20" ybr="325.50">
    </box>
    <box frame="286" outside="0" occluded="0" keyframe="0" xtl="120.70" ytl="160.70" xbr="493.20" ybr="325.50">
    </box>
    <box frame="287" outside="0" occluded="0" keyframe="0" xtl="120.70" ytl="160.70" xbr="493.20" ybr="325.50">
    </box>
    <box frame="288" outside="0" occluded="0" keyframe="0" xtl="120.70" ytl="160.70" xbr="493.20" ybr="325.50">
    </box>
    <box frame="289" outside="0" occluded="0" keyframe="0" xtl="120.70" ytl="160.70" xbr="493.20" ybr="325.50">
    </box>
    <box frame="290" outside="0" occluded="0" keyframe="0" xtl="120.70" ytl="160.70" xbr="493.20" ybr="325.50">
    </box>
    <box frame="291" outside="0" occluded="0" keyframe="0" xtl="120.70" ytl="160.70" xbr="493.20" ybr="325.50">
    </box>
    <box frame="292" outside="0" occluded="0" keyframe="0" xtl="120.70" ytl="160.70" xbr="493.20" ybr="325.50">
    </box>
    <box frame="293" outside="0" occluded="0" keyframe="0" xtl="120.70" ytl="160.70" xbr="493.20" ybr="325.50">
    </box>
    <box frame="294" outside="0" occluded="0" keyframe="0" xtl="120.70" ytl="160.70" xbr="493.20" ybr="325.50">
    </box>
    <box frame="295" outside="0" occluded="0" keyframe="0" xtl="120.70" ytl="160.70" xbr="493.20" ybr="325.50">
    </box>
    <box frame="296" outside="0" occluded="0" keyframe="0" xtl="120.70" ytl="160.70" xbr="493.20" ybr="325.50">
    </box>
    <box frame="297" outside="0" occluded="0" keyframe="0" xtl="120.70" ytl="160.70" xbr="493.20" ybr="325.50">
    </box>
    <box frame="298" outside="0" occluded="0" keyframe="0" xtl="120.70" ytl="160.70" xbr="493.20" ybr="325.50">
    </box>
    <box frame="299" outside="0" occluded="0" keyframe="0" xtl="120.70" ytl="160.70" xbr="493.20" ybr="325.50">
    </box>
  </track>
</annotations>