<?xml version="1.0" encoding="utf-8"?>
<annotations>
  <version>1.1</version>
  <meta>
    <task>
      <id>779</id>
      <name>293</name>
      <size>250</size>
      <mode>interpolation</mode>
      <overlap>0</overlap>
      <bugtracker></bugtracker>
      <created>2020-09-23 03:20:48.967357+00:00</created>
      <updated>2020-09-23 03:20:48.967380+00:00</updated>
      <start_frame>0</start_frame>
      <stop_frame>249</stop_frame>
      <frame_filter></frame_filter>
      <z_order>False</z_order>
      <labels>
        <label>
          <name>sounding object</name>
          <color>#8d3f61</color>
          <attributes>
          </attributes>
        </label>
      </labels>
      <segments>
        <segment>
          <id>779</id>
          <start>0</start>
          <stop>249</stop>
          <url>http://localhost:8080/?id=779</url>
        </segment>
      </segments>
      <owner>
        <username>lester</username>
        <email>lester0866@gmail.com</email>
      </owner>
      <assignee></assignee>
      <original_size>
        <width>480</width>
        <height>360</height>
      </original_size>
    </task>
    <dumped>2020-10-06 00:12:54.897895+00:00</dumped>
    <source>95BBXTWKR4U.mp4</source>
  </meta>
</annotations>